setup.cfg
setup.py
s3rap/__init__.py
s3rap/s3rap.py
s3rap.egg-info/PKG-INFO
s3rap.egg-info/SOURCES.txt
s3rap.egg-info/dependency_links.txt
s3rap.egg-info/requires.txt
s3rap.egg-info/top_level.txt