Metadata-Version: 1.1
Name: s3rap
Version: 0.4
Summary: AWS S3 convenience functions based on boto3.
Home-page: https://github.com/bobcolner/s3rap
Author: Bob Colner
Author-email: bcolner@gmail.com
License: MIT
Download-URL: https://github.com/bobcolner/s3rap/tarball/0.4
Keywords: aws,s3,cloud
Platform: any
Classifier: Development Status :: 4 - Beta
Classifier: Intended Audience :: Developers
Classifier: Topic :: Internet :: WWW/HTTP
Classifier: License :: OSI Approved :: MIT License
Classifier: Programming Language :: Python :: 3.3
Classifier: Programming Language :: Python :: 3.4
Classifier: Programming Language :: Python :: 3.5
